cmpl/__init__.py
cmpl/_version.py
cmpl/quantitative_MRI/__init__.py
cmpl/quantitative_MRI/mapping.py
cmpl/reconstruction/__init__.py
cmpl/reconstruction/grappa/__init__.py
cmpl/reconstruction/grappa/grappa_1D.py
cmpl/reconstruction/grappa/grappa_2D.py
cmpl/reconstruction/grappa/utils.py
cmpl/reconstruction/sense/__init__.py
cmpl/reconstruction/sense/cg.py
cmpl/segmentation/MRISegmentationTool.py
cmpl/segmentation/__init__.py
cmpl/segmentation/tools.py
cmpl/utilities/__init__.py
cmpl/utilities/df_build.py
cmpl/utilities/io.py
cmpl/utilities/utils.py
cmpl/visualization/__init__.py
cmpl/visualization/visualization.py
cmpl-0.1.7.dist-info/licenses/LICENSE
cmpl-0.1.7.dist-info/METADATA
cmpl-0.1.7.dist-info/WHEEL
cmpl-0.1.7.dist-info/top_level.txt
cmpl-0.1.7.dist-info/RECORD
