Metadata-Version: 2.4
Name: cmpl
Version: 0.1.7
Summary: CMRR MRI Processing Libraries
Author: Eisa Hedayati
License: Copyright (c) 2025 Eisa Hedayati
Classifier: Programming Language :: Python :: 3
Classifier: Operating System :: OS Independent
Classifier: License :: Other/Proprietary License
Requires-Python: >=3.10
License-File: LICENSE
Requires-Dist: h5py~=3.11.0
Requires-Dist: pandas
Requires-Dist: numpy~=1.26.3
Requires-Dist: nibabel~=5.2.0
Requires-Dist: pydicom~=2.4.4
Requires-Dist: matplotlib~=3.8.0
Requires-Dist: scipy~=1.11.4
Requires-Dist: torch
Requires-Dist: simpleitk
Requires-Dist: tqdm~=4.66.1
Requires-Dist: dicom2nifti~=2.4.11
Requires-Dist: monai~=1.3.1
Requires-Dist: ipywidgets~=8.1.3
Requires-Dist: ipython~=8.20.0
Dynamic: license-file
